[
    {
        "id": 1,
        "nombre": "Línea",
        "lista":[
            {
                "id": 1,
                "nombre": "Americana"
            },
            {
                "id": 2,
                "nombre": "Americana con cajones"
            },
            {
                "id": 3,
                "nombre": "Europea"
            },
            {
                "id": 4,
                "nombre": "Europea con cajones"
            }
        ]
    },
    {
        "id": 2,
        "nombre": "Tamaño",
        "lista":[
            {
                "id": 1,
                "nombre": "1 plaza"
            },
            {
                "id": 2,
                "nombre": "1 plaza y media"
            },
            {
                "id": 3,
                "nombre": "2 plazas"
            },
            {
                "id": 4,
                "nombre": "Queen"
            },
            {
                "id": 5,
                "nombre": "King"
            }
        ]
    },
    {
        "id": 3,
        "nombre": "Tipo de cabecera",
        "lista":[
            {
                "id": 1,
                "nombre": "Aérea"
            },
            {
                "id": 2,
                "nombre": "Pedestal"
            }
        ]
    },
    {
        "id": 4,
        "nombre": "Modelos de cabecera",
        "lista":[
            {
                "id": 1,
                "nombre": "Americanas"
            },
            {
                "id": 2,
                "nombre": "Bloques"
            },
            {
                "id": 3,
                "nombre": "Clásicas"
            },
            {
                "id": 4,
                "nombre": "Con marco"
            },
            {
                "id": 5,
                "nombre": "Coronas"
            }
        ]
    },
    {
        "id": 5,
        "nombre": "Diseños de cabecera",
        "lista":[
            {
                "id": 1,
                "nombre": "Capitoneadas"
            },
            {
                "id": 2,
                "nombre": "Clásicas"
            },
            {
                "id": 3,
                "nombre": "Cuadros"
            },
            {
                "id": 4,
                "nombre": "Líneales"
            },
            {
                "id": 5,
                "nombre": "Infantiles"
            },
            {
                "id": 6,
                "nombre": "Otras formas"
            }
        ]
    }
]