{
    "productos":[
        {
            "id": 1,
            "categoria": "cama box tarimas",
            "linea": "americanos",
            "ruta": "/productos/cama-box-tarimas/americanos/king/1/",
            "nombre": "CAMA BOX TARIMA AMERICANO KING + CABECERA AÉREA BLOQUES PISAC - FUCSIA",
            "fotos": "/assets/imagenes/productos/cama-box-tarimas/americanos/king/1/",
            "precioRegular": 1099,
            "precioNormal": 1000,
            "precioVenta": 610,
            "stock": 12,
            "sku": "K241",
            "regalos":[
                {
                    "texto": "2 almohadas",
                    "foto": "/assets/imagenes/productos/almohadas.png"
                }
            ],
            "resumen-del-producto":[
                {
                    "línea": "Americanos",
                    "tamaño": "King",
                    "tipo-de-cabecera": "Aérea",
                    "modelo-de-cabecera": "Pisac"
                }
            ],
            "tipo-de-envio": "Envío preferente",
            "detalles-del-producto":[
                {
                    "sku": "K241",
                    "línea-cama-box": "Americanos",
                    "tamaño": "King",
                    "tipo-de-cabecera": "Aérea con patas",
                    "diseño-de-cabecera": "Bloques",
                    "modelo-de-cabecera": "Pisac"
                }
            ],
            "descripciones":[
                {
                    "titulo": "Cama box tarima",
                    "descripcion":[
                        {
                            "sku": "K241",
                            "línea-cama-box": "Americanos",
                            "tamaño": "King",
                            "tipo-de-cabecera": "Aérea con patas",
                            "diseño-de-cabecera": "Bloques",
                            "modelo-de-cabecera": "Pisac"
                        }
                    ]
                },
                {
                    "titulo": "Colchón",
                    "descripcion":[
                        {
                            "marca": "Kamas",
                            "modelo": "Sarki"
                        }
                    ]
                },
                {
                    "titulo": "Cabecera",
                    "descripcion":[
                        {
                            "sku": "K241",
                            "línea-cama-box": "Americanos",
                            "tamaño": "King",
                            "tipo-de-cabecera": "Aérea con patas",
                            "diseño-de-cabecera": "Bloques",
                            "modelo-de-cabecera": "Pisac"
                        }
                    ]
                },
                {
                    "titulo": "Puff",
                    "descripcion":[
                        {
                            "sku": "K241",
                            "línea-cama-box": "Americanos",
                            "tamaño": "King",
                            "tipo-de-cabecera": "Aérea con patas",
                            "diseño-de-cabecera": "Bloques",
                            "modelo-de-cabecera": "Pisac"
                        }
                    ]
                }
            ]
        }
    ]
}