{
    "productos":[
        {
            "id": 1,
            "categoria": "cama box tarimas",
            "subcategoria": "europeos",
            "ruta": "/productos/cama-box-tarimas/europeos/1-plaza-y-media/1/",
            "nombre": "CAMA BOX TARIMA EUROPEO 1 PLAZA Y MEDIA + CABECERA AÉREA PEDESTAL EMPERATRIZ - PLATA",
            "fotos": "/assets/imagenes/productos/cama-box-tarimas/europeos/1-plaza-y-media/pedestales/emperatriz/1/",
            "colores": "si",
            "precioRegular": 1099,
            "precioNormal": 1000,
            "precioVenta": 610,
            "stock": 12,
            "sku": "K2153221N10",
            "resumen-del-producto":[
                {
                    "línea": "Europeos",
                    "tamaño": "1 plaza y media",
                    "tipo-de-cabecera": "Pedestal",
                    "modelo-de-cabecera": "Emperatriz"
                }
            ],
            "tipo-de-envio": "Envío preferente",
            "detalles-del-producto":[
                {
                    "sku": "K2153221N10",
                    "línea": "Europeos",
                    "tamaño": "1 plaza y media",
                    "tipo-de-cabecera": "Pedestal",
                    "diseño-de-cabecera": "Americanas",
                    "modelo-de-cabecera": "Capitoneadas",
                    "tipo-de-brazo": "Brazo recto"
                }
            ],
            "descripciones":[
                {
                    "titulo": "Cama box tarima",
                    "descripcion":[
                        {
                            "madera": "Pino americano seco al horno.",
                            "refuerzos": "centrales y laterales.",
                            "láminas": "MDF de 3mm.",
                            "tela": "Piel de potro",
                            "patas": "Cromadas",
                            "garantía": "2 años"
                        }
                    ]
                },
                {
                    "titulo": "Cabecera",
                    "descripcion":[
                        {
                            "madera": "Pino americano seco al horno.",
                            "espuma": "Zebra de alta densidad",
                            "láminas": "MDF de 3mm.",
                            "tela": "Piel de potro",
                            "patas": "De manera",
                            "botones": "clásicos o acrílicos",
                            "garantía": "2 años"
                        }
                    ]
                }
            ]
        }
    ]
}
